pavement.py
pyage_forams/__init__.py
pyage_forams/utils.py
pyage_forams.egg-info/PKG-INFO
pyage_forams.egg-info/SOURCES.txt
pyage_forams.egg-info/dependency_links.txt
pyage_forams.egg-info/top_level.txt
pyage_forams/conf/__init__.py
pyage_forams/conf/dummy_conf.py
pyage_forams/conf/foram_pt.py
pyage_forams/conf/foram_simple.py
pyage_forams/conf/distributed2d/__init__.py
pyage_forams/conf/distributed2d/common.py
pyage_forams/conf/distributed2d/lowerleft.py
pyage_forams/conf/distributed2d/lowerright.py
pyage_forams/conf/distributed2d/upperleft.py
pyage_forams/conf/distributed2d/upperright.py
pyage_forams/conf/distributed3d/__init__.py
pyage_forams/conf/distributed3d/common.py
pyage_forams/conf/distributed3d/lowerleftback.py
pyage_forams/conf/distributed3d/lowerleftfront.py
pyage_forams/conf/distributed3d/lowerrightback.py
pyage_forams/conf/distributed3d/lowerrightfront.py
pyage_forams/conf/distributed3d/upperleftback.py
pyage_forams/conf/distributed3d/upperleftfront.py
pyage_forams/conf/distributed3d/upperrightback.py
pyage_forams/conf/distributed3d/upperrightfront.py
pyage_forams/conf/test/__init__.py
pyage_forams/conf/test/test_conf.py
pyage_forams/solutions/__init__.py
pyage_forams/solutions/cell.py
pyage_forams/solutions/environment.py
pyage_forams/solutions/foram.py
pyage_forams/solutions/genom.py
pyage_forams/solutions/insolation_meter.py
pyage_forams/solutions/statistics.py
pyage_forams/solutions/test_cell.py
pyage_forams/solutions/test_distributed.py
pyage_forams/solutions/test_environment.py
pyage_forams/solutions/test_foram.py
pyage_forams/solutions/test_insolation.py
pyage_forams/solutions/thermometer.py
pyage_forams/solutions/agent/__init__.py
pyage_forams/solutions/agent/aggregate.py
pyage_forams/solutions/agent/remote_aggegate.py
pyage_forams/solutions/agent/shadow_cell.py
pyage_forams/solutions/distributed/__init__.py
pyage_forams/solutions/distributed/neighbour_matcher.py
pyage_forams/solutions/distributed/request.py
pyage_forams/solutions/distributed/requests/__init__.py
pyage_forams/solutions/distributed/requests/migrate.py