Metadata-Version: 1.1
Name: pyage-forams
Version: 1.0.5
Summary: Forams package for Pyage platform
Home-page: UNKNOWN
Author: Maciej Kaziród
Author-email: kazirod.maciej@gmail.com
License: UNKNOWN
Platform: UNKNOWN
Requires: matplotlib
Requires: pyage
